odoo/addons/product_weighable_default_weight/README.rst
odoo/addons/product_weighable_default_weight/__init__.py
odoo/addons/product_weighable_default_weight/__manifest__.py
odoo/addons/product_weighable_default_weight/hooks.py
odoo/addons/product_weighable_default_weight/demo/res_groups.xml
odoo/addons/product_weighable_default_weight/i18n/fr.po
odoo/addons/product_weighable_default_weight/i18n/product_weighable_default_weight.pot
odoo/addons/product_weighable_default_weight/models/__init__.py
odoo/addons/product_weighable_default_weight/models/product_product.py
odoo/addons/product_weighable_default_weight/models/product_template.py
odoo/addons/product_weighable_default_weight/readme/CONTRIBUTORS.rst
odoo/addons/product_weighable_default_weight/readme/DESCRIPTION.rst
odoo/addons/product_weighable_default_weight/static/description/icon.png
odoo/addons/product_weighable_default_weight/static/description/index.html
odoo/addons/product_weighable_default_weight/tests/__init__.py
odoo/addons/product_weighable_default_weight/tests/test_module.py
odoo12_addon_product_weighable_default_weight-12.0.1.0.0.99.dev2.dist-info/METADATA
odoo12_addon_product_weighable_default_weight-12.0.1.0.0.99.dev2.dist-info/WHEEL
odoo12_addon_product_weighable_default_weight-12.0.1.0.0.99.dev2.dist-info/top_level.txt
odoo12_addon_product_weighable_default_weight-12.0.1.0.0.99.dev2.dist-info/RECORD
